kasai/__init__.py
kasai/__main__.py
kasai/banner.txt
kasai/bot.py
kasai/channels.py
kasai/entity_factory.py
kasai/errors.py
kasai/events.py
kasai/games.py
kasai/messages.py
kasai/py.typed
kasai/streams.py
kasai/traits.py
kasai/twitch.py
kasai/users.py
kasai/ux.py
hikari_kasai-0.10a0.dist-info/LICENSE
hikari_kasai-0.10a0.dist-info/METADATA
hikari_kasai-0.10a0.dist-info/WHEEL
hikari_kasai-0.10a0.dist-info/top_level.txt
hikari_kasai-0.10a0.dist-info/RECORD
