Metadata-Version: 2.1
Name: hikari-kasai
Version: 0.10a0
Summary: A bridge between Discord and Twitch chat.
Home-page: https://github.com/parafoxia/hikari-kasai
Author: Ethan Henderson
Author-email: ethan.henderson.1998@gmail.com
License: BSD 3-Clause 'New' or 'Revised' License
Project-URL: Documentation, https://parafoxia.github.io/hikari-kasai/kasai
Project-URL: Source, https://github.com/parafoxia/hikari-kasai
Project-URL: Bug Tracker, https://github.com/parafoxia/hikari-kasai/issues
Project-URL: CI, https://github.com/parafoxia/hikari-kasai/actions
Project-URL: Changelog, https://github.com/parafoxia/hikari-kasai/releases
Classifier: Development Status :: 3 - Alpha
Classifier: Environment :: Console
Classifier: Framework :: AsyncIO
Classifier: Intended Audience :: Developers
Classifier: License :: OSI Approved :: BSD License
Classifier: Natural Language :: English
Classifier: Operating System :: MacOS
Classifier: Operating System :: Microsoft :: Windows
Classifier: Operating System :: OS Independent
Classifier: Operating System :: POSIX
Classifier: Operating System :: Unix
Classifier: Programming Language :: Python :: 3
Classifier: Programming Language :: Python :: 3 :: Only
Classifier: Programming Language :: Python :: 3.8
Classifier: Programming Language :: Python :: 3.9
Classifier: Programming Language :: Python :: 3.10
Classifier: Programming Language :: Python :: Implementation :: CPython
Classifier: Topic :: Communications :: Chat
Classifier: Topic :: Communications :: Chat :: Internet Relay Chat
Classifier: Topic :: Internet
Classifier: Typing :: Typed
Requires-Python: >=3.8.0,<3.11
License-File: LICENSE
Requires-Dist: hikari (~=2.0.0.dev110)
Requires-Dist: irctokens (<3,>=2.0)
Requires-Dist: python-dateutil (<3,>=2.8.2)
